README.md
setup.cfg
setup.py
pyflames/__init__.py
pyflames/pyflames.py
pyflames/setup.py
pyflames.egg-info/PKG-INFO
pyflames.egg-info/SOURCES.txt
pyflames.egg-info/dependency_links.txt
pyflames.egg-info/entry_points.txt
pyflames.egg-info/top_level.txt