Metadata-Version: 2.1
Name: pyflames
Version: 1.3.3
Summary: Python library to compare two strings and return their relationship status as per Asia's famous FLAMES Game.
Home-page: https://github.com/shyams1993/pyflames
Author: SHYAM SALIL
Author-email: shyamsalil1993@gmail.com
License: MIT
Keywords: INTERESTING!
Platform: UNKNOWN
Classifier: Development Status :: 4 - Beta
Classifier: Intended Audience :: Developers
Classifier: Topic :: Software Development :: Build Tools
Classifier: License :: OSI Approved :: MIT License
Classifier: Programming Language :: Python :: 3.4
Classifier: Programming Language :: Python :: 3.5
Classifier: Programming Language :: Python :: 3.6
Requires-Python: >=3.1
